setup.py
lmstudio_api/__init__.py
lmstudio_api.egg-info/PKG-INFO
lmstudio_api.egg-info/SOURCES.txt
lmstudio_api.egg-info/dependency_links.txt
lmstudio_api.egg-info/top_level.txt